ormvana.py
ormvana-0.0.1.dist-info/LICENSE
ormvana-0.0.1.dist-info/METADATA
ormvana-0.0.1.dist-info/WHEEL
ormvana-0.0.1.dist-info/top_level.txt
ormvana-0.0.1.dist-info/RECORD
