Metadata-Version: 2.1
Name: ormvana
Version: 0.0.1
Summary: A minimalist ORM for the power user — Releases you from the sufferings of the traditional ORM world.
Home-page: https://github.com/SkullTech/ormvana
Author: Sumit Ghosh
Author-email: sumit@sumit-ghosh.com
License: MIT
